Metadata-Version: 2.1
Name: fairometrics
Version: 24.10.1
Summary: A collection of pre-certified fairness metrics supported by Fairo.
Home-page: https://www.fairo.ai
Author: Fairo Systems, Inc.
Author-email: support@fairo.ai
License: Apache-2.0
Keywords: fairo fairness AI governance metrics
Classifier: Programming Language :: Python :: 3.7
Classifier: Programming Language :: Python :: 3.8
Classifier: Programming Language :: Python :: 3.9
Classifier: Programming Language :: Python :: 3.10
Classifier: License :: OSI Approved :: Apache Software License
Classifier: Operating System :: OS Independent
